LICENSE
MANIFEST.in
README.rst
setup.py
django_payzen/__init__.py
django_payzen/admin.py
django_payzen/app_settings.py
django_payzen/apps.py
django_payzen/constants.py
django_payzen/forms.py
django_payzen/models.py
django_payzen/signals.py
django_payzen/tools.py
django_payzen/urls.py
django_payzen/views.py
django_payzen.egg-info/PKG-INFO
django_payzen.egg-info/SOURCES.txt
django_payzen.egg-info/dependency_links.txt
django_payzen.egg-info/pbr.json
django_payzen.egg-info/requires.txt
django_payzen.egg-info/top_level.txt
django_payzen/migrations/0001_initial.py
django_payzen/migrations/0002_auto_20141024_0822.py
django_payzen/migrations/0003_auto_20141027_1647.py
django_payzen/migrations/0004_auto_20141221_2140.py
django_payzen/migrations/__init__.py
django_payzen/templates/django_payzen/auto_submit_form.html
django_payzen/templates/django_payzen/form.html
django_payzen/templatetags/__init__.py
django_payzen/templatetags/payzen_extras.py
django_payzen/tests/__init__.py
django_payzen/tests/data.py
django_payzen/tests/payzen_init/__init__.py
django_payzen/tests/payzen_init/tests.py
django_payzen/tests/payzen_response/__init__.py
django_payzen/tests/payzen_response/tests.py
django_payzen/tests/request_data/__init__.py
django_payzen/tests/request_data/tests.py
tests/__init__.py
tests/test_cmd.py
tests/urls.py