Metadata-Version: 1.1
Name: django-payzen
Version: 1.0.5
Summary: Django app to manage payments with Payzen ETP
Home-page: https://github.com/bsvetchine/django-payzen
Author: Bertrand Svetchine
Author-email: bertrand.svetchine@gmail.com
License: MIT
Platform: UNKNOWN
Classifier: Development Status :: 4 - Beta
Classifier: Environment :: Web Environment
Classifier: Intended Audience :: Developers
Classifier: Operating System :: OS Independent
Classifier: Programming Language :: Python :: 2
Classifier: Programming Language :: Python :: 2.6
Classifier: Programming Language :: Python :: 2.7
Classifier: Programming Language :: Python :: 3
Classifier: Programming Language :: Python :: 3.2
Classifier: Programming Language :: Python :: 3.3
Classifier: Programming Language :: Python :: 3.4
Classifier: Framework :: Django
Classifier: Topic :: Software Development
